faq/__init__.py
faq/admin.py
faq/models.py
faq/urls.py
faq/migrations/0001_initial.py
faq/migrations/__init__.py
faq/templates/faq/inclusion_tags/faq_detail.html
faq/templates/faq/inclusion_tags/faq_header.html
faq/templates/faq/inclusion_tags/faq_listing_item.html
faq/tests/__init__.py
faq/tests/manage.py
faq/tests/test_admin.py
faq/tests/test_model.py
faq/tests/urls.py
faq/tests/requirements/19.txt
faq/tests/settings/19.py
faq/tests/settings/__init__.py
faq/tests/templates/base.html
jmbo_faq-0.1.0.dist-info/DESCRIPTION.rst
jmbo_faq-0.1.0.dist-info/METADATA
jmbo_faq-0.1.0.dist-info/RECORD
jmbo_faq-0.1.0.dist-info/WHEEL
jmbo_faq-0.1.0.dist-info/metadata.json
jmbo_faq-0.1.0.dist-info/top_level.txt
